{
  "name": "Mackay_Crk_At_Cc_Haigh_Landing_Nr_Hilton_Head_Sc",
  "country": "United States",
  "continent": "Americas",
  "latitude": 32.2285,
  "longitude": -80.788417,
  "timezone": "America/New_York",
  "source": {
    "name": "TICON-4",
    "url": "https://www.seanoe.org/data/00980/109129/",
    "id": "mackay_crk_at_cc_haigh_landing_nr_hilton_head_sc-2176702-usa-usgs",
    "published_harmonics": true
  },
  "license": {
    "type": "cc-by-4.0",
    "commercial_use": true,
    "url": "https://creativecommons.org/licenses/by/4.0/"
  },
  "disclaimers": "No obvious issues",
  "datums": {
    "MHHW": 1.009,
    "MHW": 1.009,
    "MSL": -0.064,
    "MTL": -0.075,
    "MLW": -1.158,
    "MLLW": -1.158,
    "LAT": -1.877
  },
  "type": "reference",
  "harmonic_constituents": [
    {
      "name": "M2",
      "amplitude": 1.06690192,
      "phase": 27.158349999999984
    },
    {
      "name": "N2",
      "amplitude": 0.2374374,
      "phase": 13.90792399999998
    },
    {
      "name": "S2",
      "amplitude": 0.16535847,
      "phase": 59.97726499999999
    },
    {
      "name": "K2",
      "amplitude": 0.04013327999999999,
      "phase": 53.810663999999974
    },
    {
      "name": "2N2",
      "amplitude": 0.02559167,
      "phase": 28.85058300000003
    },
    {
      "name": "S1",
      "amplitude": 0.02118823,
      "phase": 172.875003
    },
    {
      "name": "K1",
      "amplitude": 0.11286536999999999,
      "phase": 206.67939
    },
    {
      "name": "P1",
      "amplitude": 0.0384438,
      "phase": 208.138518
    },
    {
      "name": "O1",
      "amplitude": 0.08082054,
      "phase": 210.748247
    },
    {
      "name": "Q1",
      "amplitude": 0.01704164,
      "phase": 209.72629
    },
    {
      "name": "M1",
      "amplitude": 0.01274286,
      "phase": 127.22069799999997
    },
    {
      "name": "M4",
      "amplitude": 0.05791092,
      "phase": 228.743713
    },
    {
      "name": "MM",
      "amplitude": 0.0146787,
      "phase": 253.947834
    },
    {
      "name": "MF",
      "amplitude": 0.00969653,
      "phase": 114.50183500000003
    },
    {
      "name": "SA",
      "amplitude": 0.12268992000000001,
      "phase": 173.65859999999998
    },
    {
      "name": "SSA",
      "amplitude": 0.08693585000000001,
      "phase": 66.29862700000001
    },
    {
      "name": "T2",
      "amplitude": 0.01855682,
      "phase": 43.50196799999998
    },
    {
      "name": "J1",
      "amplitude": 0.006422560000000001,
      "phase": 204.458091
    },
    {
      "name": "L2",
      "amplitude": 0.04818551,
      "phase": 6.516749000000004
    },
    {
      "name": "R2",
      "amplitude": 0.013639140000000001,
      "phase": 287.41432
    },
    {
      "name": "2Q1",
      "amplitude": 0.00399748,
      "phase": 145.955018
    },
    {
      "name": "MSF",
      "amplitude": 0.01787345,
      "phase": 34.941322000000014
    },
    {
      "name": "MSQM",
      "amplitude": 0.00925656,
      "phase": 35.30026299999997
    },
    {
      "name": "EP2",
      "amplitude": 0.012329030000000001,
      "phase": 64.81719299999997
    },
    {
      "name": "M3",
      "amplitude": 0.024797129999999997,
      "phase": 163.70281799999998
    },
    {
      "name": "MU2",
      "amplitude": 0.04133279,
      "phase": 74.60873200000003
    },
    {
      "name": "MTM",
      "amplitude": 0.01147826,
      "phase": 42.04549099999997
    },
    {
      "name": "NU2",
      "amplitude": 0.04417591,
      "phase": 2.6190310000000068
    },
    {
      "name": "LAMBDA2",
      "amplitude": 0.02213321,
      "phase": 6.505622000000017
    },
    {
      "name": "MN4",
      "amplitude": 0.02216497,
      "phase": 218.02127
    },
    {
      "name": "MS4",
      "amplitude": 0.025761259999999998,
      "phase": 275.684679
    },
    {
      "name": "MKS2",
      "amplitude": 0.014519230000000001,
      "phase": 208.928113
    },
    {
      "name": "N4",
      "amplitude": 0.00482764,
      "phase": 242.930831
    },
    {
      "name": "M6",
      "amplitude": 0.029934699999999998,
      "phase": 108.77653700000002
    },
    {
      "name": "M8",
      "amplitude": 0.00715969,
      "phase": 273.727311
    },
    {
      "name": "S4",
      "amplitude": 0.007001810000000001,
      "phase": 74.55939999999998
    },
    {
      "name": "OO1",
      "amplitude": 0.00896746,
      "phase": 237.465663
    },
    {
      "name": "S3",
      "amplitude": 0.01507927,
      "phase": 273.900921
    },
    {
      "name": "MA2",
      "amplitude": 0.03140787,
      "phase": 281.780208
    },
    {
      "name": "MB2",
      "amplitude": 0.03052699,
      "phase": 356.01106
    },
    {
      "name": "T3",
      "amplitude": 0.012651079999999999,
      "phase": 178.60054000000002
    },
    {
      "name": "R3",
      "amplitude": 0.01177071,
      "phase": 4.196413000000007
    },
    {
      "name": "RHO1",
      "amplitude": 0.00522181,
      "phase": 195.384838
    },
    {
      "name": "SGM",
      "amplitude": 0.00094138,
      "phase": 108.338502
    },
    {
      "name": "3L2",
      "amplitude": 0.005861389999999999,
      "phase": 42.49774600000001
    },
    {
      "name": "3N2",
      "amplitude": 0.02111686,
      "phase": 312.305347
    },
    {
      "name": "2SM2",
      "amplitude": 0.00566755,
      "phase": 135.75354900000002
    },
    {
      "name": "2MS6",
      "amplitude": 0.014391750000000002,
      "phase": 147.06825300000003
    },
    {
      "name": "2MK5",
      "amplitude": 0.00551789,
      "phase": 150.644701
    },
    {
      "name": "2MO5",
      "amplitude": 0.00408395,
      "phase": 313.322943
    }
  ],
  "epoch": {
    "start": "2023-03-22",
    "end": "2025-04-30"
  }
}
