{
  "name": "Oosterschelde_14",
  "country": "Netherlands",
  "continent": "Europe",
  "latitude": 51.721544,
  "longitude": 3.675918,
  "timezone": "Europe/Amsterdam",
  "source": {
    "name": "TICON-4",
    "url": "https://www.seanoe.org/data/00980/109129/",
    "id": "oosterschelde_14-oostsde14-nld-rws",
    "published_harmonics": true
  },
  "license": {
    "type": "cc-by-4.0",
    "commercial_use": true,
    "url": "https://creativecommons.org/licenses/by/4.0/"
  },
  "disclaimers": "No obvious issues",
  "datums": {
    "MHHW": 1.413,
    "MHW": 1.414,
    "MSL": 0.118,
    "MTL": 0.119,
    "MLW": -1.176,
    "MLLW": -1.176,
    "LAT": -1.744
  },
  "type": "reference",
  "harmonic_constituents": [
    {
      "name": "M2",
      "amplitude": 1.18357196,
      "phase": 52.48513000000003
    },
    {
      "name": "N2",
      "amplitude": 0.18651092,
      "phase": 24.48017900000002
    },
    {
      "name": "S2",
      "amplitude": 0.31839651,
      "phase": 108.60294199999998
    },
    {
      "name": "K2",
      "amplitude": 0.09365332999999999,
      "phase": 112.60896500000001
    },
    {
      "name": "2N2",
      "amplitude": 0.030741900000000003,
      "phase": 18.301033000000018
    },
    {
      "name": "S1",
      "amplitude": 0.00711906,
      "phase": 4.231155999999999
    },
    {
      "name": "K1",
      "amplitude": 0.07174719,
      "phase": 356.785795
    },
    {
      "name": "P1",
      "amplitude": 0.032794340000000005,
      "phase": 340.131973
    },
    {
      "name": "O1",
      "amplitude": 0.10744717,
      "phase": 183.422948
    },
    {
      "name": "Q1",
      "amplitude": 0.03999558,
      "phase": 130.36636199999998
    },
    {
      "name": "M1",
      "amplitude": 0.00266722,
      "phase": 52.82456100000002
    },
    {
      "name": "M4",
      "amplitude": 0.11955693,
      "phase": 90.09140500000001
    },
    {
      "name": "MM",
      "amplitude": 0.00587998,
      "phase": 100.864486
    },
    {
      "name": "MF",
      "amplitude": 0.00769424,
      "phase": 132.21308799999997
    },
    {
      "name": "SA",
      "amplitude": 0.09794847000000001,
      "phase": 224.697729
    },
    {
      "name": "SSA",
      "amplitude": 0.01648948,
      "phase": 186.794556
    },
    {
      "name": "T2",
      "amplitude": 0.06239873,
      "phase": 29.258234000000016
    },
    {
      "name": "J1",
      "amplitude": 0.00447099,
      "phase": 105.76325500000002
    },
    {
      "name": "L2",
      "amplitude": 0.08061209,
      "phase": 79.169602
    },
    {
      "name": "R2",
      "amplitude": 0.03681772,
      "phase": 206.096266
    },
    {
      "name": "2Q1",
      "amplitude": 0.006878189999999999,
      "phase": 73.49399199999999
    },
    {
      "name": "MSF",
      "amplitude": 0.026900729999999998,
      "phase": 28.87116400000002
    },
    {
      "name": "MSQM",
      "amplitude": 0.0028886899999999997,
      "phase": 231.627418
    },
    {
      "name": "EP2",
      "amplitude": 0.01878533,
      "phase": 144.46754999999996
    },
    {
      "name": "M3",
      "amplitude": 0.00500554,
      "phase": 119.99117000000001
    },
    {
      "name": "MU2",
      "amplitude": 0.09726877,
      "phase": 171.35301600000003
    },
    {
      "name": "MTM",
      "amplitude": 0.00438463,
      "phase": 192.373126
    },
    {
      "name": "NU2",
      "amplitude": 0.06800491,
      "phase": 24.302557999999976
    },
    {
      "name": "LAMBDA2",
      "amplitude": 0.0410764,
      "phase": 74.92056400000001
    },
    {
      "name": "MN4",
      "amplitude": 0.04072613,
      "phase": 64.65236700000003
    },
    {
      "name": "MS4",
      "amplitude": 0.08127207,
      "phase": 148.63894400000004
    },
    {
      "name": "MKS2",
      "amplitude": 0.038252100000000004,
      "phase": 188.579375
    },
    {
      "name": "N4",
      "amplitude": 0.010901540000000001,
      "phase": 54.614756
    },
    {
      "name": "M6",
      "amplitude": 0.04865869,
      "phase": 58.899653
    },
    {
      "name": "M8",
      "amplitude": 0.01081458,
      "phase": 90.69808699999999
    },
    {
      "name": "S4",
      "amplitude": 0.00786404,
      "phase": 243.450962
    },
    {
      "name": "OO1",
      "amplitude": 0.00406286,
      "phase": 139.94833700000004
    },
    {
      "name": "S3",
      "amplitude": 0.00338163,
      "phase": 52.34481699999998
    },
    {
      "name": "MA2",
      "amplitude": 0.21009618,
      "phase": 34.66470099999998
    },
    {
      "name": "MB2",
      "amplitude": 0.19599618,
      "phase": 239.93175300000001
    },
    {
      "name": "T3",
      "amplitude": 0.0009644300000000001,
      "phase": 3.0747840000000224
    },
    {
      "name": "R3",
      "amplitude": 0.0086529,
      "phase": 248.341458
    },
    {
      "name": "RHO1",
      "amplitude": 0.00852447,
      "phase": 126.31985900000001
    },
    {
      "name": "SGM",
      "amplitude": 0.00112749,
      "phase": 50.34227800000002
    },
    {
      "name": "3L2",
      "amplitude": 0.007283410000000001,
      "phase": 211.96657
    },
    {
      "name": "3N2",
      "amplitude": 0.0034093,
      "phase": 97.80154299999998
    },
    {
      "name": "2SM2",
      "amplitude": 0.03036498,
      "phase": 341.087978
    },
    {
      "name": "2MS6",
      "amplitude": 0.05010441,
      "phase": 109.33098100000001
    },
    {
      "name": "2MK5",
      "amplitude": 0.0049616,
      "phase": 208.398342
    },
    {
      "name": "2MO5",
      "amplitude": 0.00677227,
      "phase": 224.302064
    }
  ],
  "epoch": {
    "start": "2004-12-29",
    "end": "2023-12-30"
  }
}
