{
  "name": "Soma",
  "country": "Japan",
  "continent": "Asia",
  "latitude": 37.83055,
  "longitude": 140.961667,
  "timezone": "Asia/Tokyo",
  "source": {
    "name": "TICON-4",
    "url": "https://www.seanoe.org/data/00980/109129/",
    "id": "soma-gs18-jpn-jodc_giaj",
    "published_harmonics": true
  },
  "license": {
    "type": "cc-by-4.0",
    "commercial_use": true,
    "url": "https://creativecommons.org/licenses/by/4.0/"
  },
  "disclaimers": "Possible datum issues",
  "datums": {
    "MHHW": 0.402,
    "MHW": 0.401,
    "MSL": 0.015,
    "MTL": 0.037,
    "MLW": -0.328,
    "MLLW": -0.331,
    "LAT": -1.131
  },
  "type": "reference",
  "harmonic_constituents": [
    {
      "name": "M2",
      "amplitude": 0.33027768,
      "phase": 196.40436
    },
    {
      "name": "N2",
      "amplitude": 0.043438559999999994,
      "phase": 183.071753
    },
    {
      "name": "S2",
      "amplitude": 0.15312125,
      "phase": 231.07425
    },
    {
      "name": "K2",
      "amplitude": 0.043524450000000006,
      "phase": 225.943233
    },
    {
      "name": "2N2",
      "amplitude": 0.0040845199999999995,
      "phase": 201.581
    },
    {
      "name": "S1",
      "amplitude": 0.00636939,
      "phase": 215.93591
    },
    {
      "name": "K1",
      "amplitude": 0.24435189000000002,
      "phase": 31.051049999999975
    },
    {
      "name": "P1",
      "amplitude": 0.07891922,
      "phase": 28.470758999999987
    },
    {
      "name": "O1",
      "amplitude": 0.19643639000000002,
      "phase": 14.376747000000023
    },
    {
      "name": "Q1",
      "amplitude": 0.041203529999999995,
      "phase": 4.410990000000027
    },
    {
      "name": "M1",
      "amplitude": 0.01086711,
      "phase": 289.345234
    },
    {
      "name": "M4",
      "amplitude": 0.0019190499999999998,
      "phase": 250.106413
    },
    {
      "name": "MM",
      "amplitude": 0.00643864,
      "phase": 128.053062
    },
    {
      "name": "MF",
      "amplitude": 0.00406502,
      "phase": 126.51158700000002
    },
    {
      "name": "SA",
      "amplitude": 0.11655798,
      "phase": 180.077941
    },
    {
      "name": "SSA",
      "amplitude": 0.00962118,
      "phase": 266.37417600000003
    },
    {
      "name": "T2",
      "amplitude": 0.00950282,
      "phase": 227.655258
    },
    {
      "name": "J1",
      "amplitude": 0.011388249999999999,
      "phase": 46.906948
    },
    {
      "name": "L2",
      "amplitude": 0.011489689999999999,
      "phase": 213.295194
    },
    {
      "name": "R2",
      "amplitude": 0.00069704,
      "phase": 257.077007
    },
    {
      "name": "2Q1",
      "amplitude": 0.005692279999999999,
      "phase": 358.335879
    },
    {
      "name": "MSF",
      "amplitude": 0.0011162,
      "phase": 179.521664
    },
    {
      "name": "MSQM",
      "amplitude": 0.00032099,
      "phase": 10.059913999999992
    },
    {
      "name": "EP2",
      "amplitude": 0.00187041,
      "phase": 200.757459
    },
    {
      "name": "M3",
      "amplitude": 0.00648202,
      "phase": 49.41593899999998
    },
    {
      "name": "MU2",
      "amplitude": 0.00755324,
      "phase": 207.78481
    },
    {
      "name": "MTM",
      "amplitude": 0.0022081600000000002,
      "phase": 143.07775300000003
    },
    {
      "name": "NU2",
      "amplitude": 0.008666749999999999,
      "phase": 180.712983
    },
    {
      "name": "LAMBDA2",
      "amplitude": 0.00315751,
      "phase": 202.204719
    },
    {
      "name": "MN4",
      "amplitude": 0.00071492,
      "phase": 121.32466299999999
    },
    {
      "name": "MS4",
      "amplitude": 0.00144927,
      "phase": 54.72945199999998
    },
    {
      "name": "MKS2",
      "amplitude": 0.00070868,
      "phase": 334.614944
    },
    {
      "name": "N4",
      "amplitude": 0.00016449,
      "phase": 33.25869
    },
    {
      "name": "M6",
      "amplitude": 0.00033136,
      "phase": 149.687009
    },
    {
      "name": "M8",
      "amplitude": 0.00044674,
      "phase": 259.494507
    },
    {
      "name": "S4",
      "amplitude": 0.00105698,
      "phase": 0.2607669999999871
    },
    {
      "name": "OO1",
      "amplitude": 0.00662564,
      "phase": 69.44434899999999
    },
    {
      "name": "S3",
      "amplitude": 0.0022447400000000003,
      "phase": 121.577426
    },
    {
      "name": "MA2",
      "amplitude": 0.00176501,
      "phase": 36.07403599999998
    },
    {
      "name": "MB2",
      "amplitude": 0.00154668,
      "phase": 356.326429
    },
    {
      "name": "T3",
      "amplitude": 0.00254297,
      "phase": 83.071144
    },
    {
      "name": "R3",
      "amplitude": 0.00233367,
      "phase": 266.597903
    },
    {
      "name": "RHO1",
      "amplitude": 0.00772247,
      "phase": 7.052081999999984
    },
    {
      "name": "SGM",
      "amplitude": 0.00661192,
      "phase": 174.03576099999998
    },
    {
      "name": "3L2",
      "amplitude": 0.00235888,
      "phase": 191.92028
    },
    {
      "name": "3N2",
      "amplitude": 0.0036408499999999997,
      "phase": 150.683157
    },
    {
      "name": "2SM2",
      "amplitude": 0.0009211099999999999,
      "phase": 99.618923
    },
    {
      "name": "2MS6",
      "amplitude": 0.0007870900000000001,
      "phase": 298.224476
    },
    {
      "name": "2MK5",
      "amplitude": 0.00074783,
      "phase": 219.09001
    },
    {
      "name": "2MO5",
      "amplitude": 0.00057429,
      "phase": 347.653085
    }
  ],
  "epoch": {
    "start": "2004-12-30",
    "end": "2023-12-31"
  }
}
